Metadata-Version: 1.1
Name: sqlconnection
Version: 0.1.8
Summary: SQL Connections and Queries Handler
Home-page: https://github.com/ByPrice/sqlconnection
Author: Yogesh Yadav
Author-email: yogesh@byprice.com
License: MIT
Download-URL: https://github.com/ByPrice/sqlconnection
Keywords: postgres,psql,postgresql
Platform: cross-platfom
Platform: platform-independent
Classifier: Development Status :: 3 - Alpha
Classifier: Intended Audience :: Developers
Classifier: Topic :: Software Development :: Build Tools
Classifier: Programming Language :: Python :: 3.6
